lens2/__init__.py
lens2/constants.py
lens2/lens2.py
lens2/setup.py
lens2/utils.py
lens2/board/__init__.py
lens2/board/create_board.py
lens2/board/generate_board.py
lens2/board/start_board.py
lens2/checks/__init__.py
lens2/checks/create_checks.py
lens2/checks/schema_check.py
lens2/checks/soda_cl_sql_mappings.py
lens2/lens/__init__.py
lens2/lens/create_lens.py
lens2/lens/resources/Makefile
lens2/lens/resources/docker-compose.yaml
lens2/lens/resources/env.env
lens2/lens/resources/sql_sample.sql
lens2/lens/resources/table_sample.yaml
lens2/lens/resources/view_sample.yaml
dataos_cookiecutter-0.0.5.dist-info/METADATA
dataos_cookiecutter-0.0.5.dist-info/WHEEL
dataos_cookiecutter-0.0.5.dist-info/entry_points.txt
dataos_cookiecutter-0.0.5.dist-info/top_level.txt
dataos_cookiecutter-0.0.5.dist-info/RECORD
