Metadata-Version: 2.1
Name: dataos-cookiecutter
Version: 0.0.5
Summary: Dataos Cookiecutter
Home-page: https://bitbucket.org/rubik_/dataos-cookiecutter
Author: devendrasr
Author-email: devendra@tmdc.io
Classifier: Programming Language :: Python :: 3
Classifier: License :: OSI Approved :: MIT License
Classifier: Operating System :: OS Independent
Requires-Python: >=3.7
Requires-Dist: requests ==2.25.1
Requires-Dist: python-dotenv ==1.0.1
Requires-Dist: PyYAML ==6.0.1
Requires-Dist: psycopg2-binary ==2.9.9
Requires-Dist: sql-metadata ==2.10.0
